{
  "updated": "2026-07-14T17:51:41.713715Z",
  "mode": "live",
  "cycle": 384,
  "balance": 35.83,
  "day_start_equity": 36.92,
  "daily_pnl": 0.0,
  "trades_today": 0,
  "open_positions": [],
  "strategies": {
    "mtf": {
      "trades": 0,
      "wins": 0,
      "losses": 0,
      "pnl": 0.0
    },
    "wave": {
      "trades": 0,
      "wins": 0,
      "losses": 0,
      "pnl": 0.0
    },
    "wave_ltf": {
      "trades": 0,
      "wins": 0,
      "losses": 0,
      "pnl": 0.0
    }
  },
  "recent_trades": []
}