{
  "updated": "2026-06-30T22:26:07.836092Z",
  "mode": "live",
  "cycle": 482,
  "balance": 44.43,
  "day_start_equity": 40.92,
  "daily_pnl": 0.0,
  "trades_today": 0,
  "open_positions": [],
  "strategies": {
    "mtf": {
      "trades": 0,
      "wins": 0,
      "losses": 0,
      "pnl": 0.0
    },
    "wave": {
      "trades": 0,
      "wins": 0,
      "losses": 0,
      "pnl": 0.0
    },
    "wave_ltf": {
      "trades": 0,
      "wins": 0,
      "losses": 0,
      "pnl": 0.0
    }
  },
  "recent_trades": []
}